{"HelpdeskPhone":"","Message":null,"ResponseCode":0,"Success":true,"Activated":true,"Company":{"CompanyId":1,"CompanyProfileList":[{"Propertyname":"highlight","Propertyvalue":"6167D8"},{"Propertyname":"soschannel","Propertyvalue":"1"},{"Propertyname":"banner","Propertyvalue":"companyprofiles\/1\/banner.png"},{"Propertyname":"foreground","Propertyvalue":"FFFFFF"},{"Propertyname":"background","Propertyvalue":"415A92"}],"Companycode":"CSI","Companyname":"Charter Solutions","Edited":"\/Date(1339619046400+0000)\/","ExternalId":"1"},"MobileclientID":20,"Phonenumber":"17703654203"}